LICENSE
MANIFEST.in
README.txt
setup.py
atomisator/__init__.py
atomisator.enhancers.egg-info/PKG-INFO
atomisator.enhancers.egg-info/SOURCES.txt
atomisator.enhancers.egg-info/dependency_links.txt
atomisator.enhancers.egg-info/entry_points.txt
atomisator.enhancers.egg-info/namespace_packages.txt
atomisator.enhancers.egg-info/not-zip-safe
atomisator.enhancers.egg-info/requires.txt
atomisator.enhancers.egg-info/top_level.txt
atomisator/enhancers/__init__.py
atomisator/enhancers/digg.py
atomisator/enhancers/postrank.py
atomisator/enhancers/todo.txt
atomisator/enhancers/tests/__init__.py
atomisator/enhancers/tests/test_enhancers.py